aiometer/__init__.py
aiometer/_compat.py
aiometer/py.typed
aiometer/_impl/__init__.py
aiometer/_impl/amap.py
aiometer/_impl/meters.py
aiometer/_impl/run_all.py
aiometer/_impl/run_any.py
aiometer/_impl/run_on_each.py
aiometer/_impl/types.py
aiometer/_impl/utils.py
aiometer-0.5.0.dist-info/LICENSE
aiometer-0.5.0.dist-info/METADATA
aiometer-0.5.0.dist-info/WHEEL
aiometer-0.5.0.dist-info/top_level.txt
aiometer-0.5.0.dist-info/RECORD
