Metadata-Version: 2.1
Name: aiometer
Version: 0.5.0
Summary: A Python concurrency scheduling library, compatible with asyncio and trio
Author-email: Florimond Manca <florimond.manca@protonmail.com>
License: MIT
Project-URL: Homepage, https://github.com/florimondmanca/aiometer
Classifier: Development Status :: 4 - Beta
Classifier: Intended Audience :: Developers
Classifier: Framework :: AsyncIO
Classifier: Framework :: Trio
Classifier: Programming Language :: Python :: 3
Classifier: Programming Language :: Python :: 3 :: Only
Classifier: Programming Language :: Python :: 3.8
Classifier: Programming Language :: Python :: 3.9
Classifier: Programming Language :: Python :: 3.10
Classifier: Programming Language :: Python :: 3.11
Classifier: Programming Language :: Python :: 3.12
Requires-Python: >=3.8
License-File: LICENSE
Requires-Dist: anyio <5,>=3.2
Requires-Dist: exceptiongroup ; python_version < "3.11"
